dict2css/__init__.py
dict2css/serializer.py
dict2css/py.typed
dict2css/helpers.py
dict2css-0.2.4.dist-info/METADATA
dict2css-0.2.4.dist-info/top_level.txt
dict2css-0.2.4.dist-info/WHEEL
dict2css-0.2.4.dist-info/LICENSE
dict2css-0.2.4.dist-info/entry_points.txt
dict2css-0.2.4.dist-info/RECORD
