Metadata-Version: 2.1
Name: dict2css
Version: 0.2.4
Summary: A μ-library for constructing cascading style sheets from Python dictionaries.
Author-email: Dominic Davis-Foster <dominic@davis-foster.co.uk>
License: MIT
Keywords: css
Home-page: https://github.com/sphinx-toolbox/dict2css
Project-URL: Issue Tracker, https://github.com/sphinx-toolbox/dict2css/issues
Project-URL: Source Code, https://github.com/sphinx-toolbox/dict2css
Project-URL: Documentation, https://dict2css.readthedocs.io/en/latest
Platform: Windows
Platform: macOS
Platform: Linux
Classifier: Development Status :: 4 - Beta
Classifier: Intended Audience :: Developers
Classifier: License :: OSI Approved :: MIT License
Classifier: Operating System :: OS Independent
Classifier: Programming Language :: Python
Classifier: Programming Language :: Python :: 3 :: Only
Classifier: Programming Language :: Python :: 3.6
Classifier: Programming Language :: Python :: 3.7
Classifier: Programming Language :: Python :: 3.8
Classifier: Programming Language :: Python :: 3.9
Classifier: Programming Language :: Python :: Implementation :: CPython
Classifier: Programming Language :: Python :: Implementation :: PyPy
Classifier: Topic :: Software Development :: Libraries :: Python Modules
Classifier: Typing :: Typed
Requires-Python: >=3.6
Requires-Dist: css-parser==1.0.6
Requires-Dist: domdf-python-tools>=2.2.0
